{
    "GradeTime": "第1屆 第9次 臨時會",
    "PTypTitle": "保安",
    "CaseNumber": "4",
    "KidTitle": "議員提案-一般提案",
    "ComeDate": "",
    "ComeNumber": "",
    "OrgTitle": "林燕祝",
    "OrgTitle2": "郭秀珠、杜素吟、李文俊",
    "CaseCause": "大灣消防隊辦公室缺乏空調設施，隊員執勤汗如雨下，應增設冷氣器材。",
    "Content": "[{\"tag\":\"p\",\"content\":\"大灣消防隊部分設施陳舊，尤其是夏日高溫，隊員三樓辦公室冷氣無法正常運轉，亟需汰舊換新，提供舒適的工作場所。\"}]",
    "Method": "[{\"tag\":\"p\",\"content\":\"促消防局儘速換購新型冷氣機，改善工作環境。\"}]",
    "CheckDate": "",
    "CheckDesc": "照案通過。",
    "DoneDate": "2014\/08\/13",
    "DoneDesc": "照審查意見通過。",
    "SendDate": "2014\/08\/18",
    "SendNumber": "南議保安字第 1030005460號",
    "DoDesc": "本案經市府103.09.03府消秘字第1030784557號函復:\r\n一、依據貴會103年8月18日南議保安字第1030005460號函辦理。\r\n二、有關提案建請本府消防局於大灣分隊3樓辦公室安裝冷氣乙案，本府消防局業已委請冷凍空調廠商於該分隊3樓安裝落地式水冷冷氣機1台，並已於8月27日完成安裝測試，目前已可提供該分隊正常使用無虞。",
    "AttList": [],
    "RAttList": [],
    "PdfDownloadUrl": "https:\/\/bill.tncc.gov.tw\/NoPaperMeeting_TNCC\/Api\/WEB015_GenerateProposal.ashx?prono=86f11178-f271-4029-872b-e92e14b3ef0a&type=pdf",
    "CheckAttList": [],
    "DoneAttList": [],
    "ReDate": "",
    "ReDesc": "照審查意見通過。",
    "FirstDate": "2014\/08\/04",
    "FirstDesc": "",
    "SecondDate": "",
    "SecondDesc": "",
    "ThirdDate": "",
    "ThirdDesc": "",
    "ExecuteReDate": "",
    "ExecuteReNumber": "",
    "ExecuteReMemo": "本案經市府103.09.03府消秘字第1030784557號函復:\r\n一、依據貴會103年8月18日南議保安字第1030005460號函辦理。\r\n二、有關提案建請本府消防局於大灣分隊3樓辦公室安裝冷氣乙案，本府消防局業已委請冷凍空調廠商於該分隊3樓安裝落地式水冷冷氣機1台，並已於8月27日完成安裝測試，目前已可提供該分隊正常使用無虞。",
    "ErrorMessage": ""
}