{
    "GradeTime": "第1屆 第3次 定期會",
    "PTypTitle": "民政",
    "CaseNumber": "10",
    "KidTitle": "議員提案-一般提案",
    "ComeDate": "",
    "ComeNumber": "",
    "OrgTitle": "曾培雅",
    "OrgTitle2": "蔡玉枝、洪玉鳳、施重男、蔡淑惠、陳文科",
    "CaseCause": "本市東區後甲公墓一直以來影響附近房價及建設，建請市府遷移或改善，以美化市容並為地方帶來良好生活環境。",
    "Content": "[{\"tag\":\"p\",\"content\":\"因公墓鄰近住宅，居民反應對生活品質有所影響，而且人口數眾多，但因附近有公墓，建商對於此處投資意願也較低，造成地方建設較為落後，希望市府遷移或改善，以美化市容並為地方帶來良好生活環境。\"}]",
    "Method": "[{\"tag\":\"p\",\"content\":\"如案由。\"}]",
    "CheckDate": "",
    "CheckDesc": "函送市府研辦。",
    "DoneDate": "2012\/06\/06",
    "DoneDesc": "照審查意見通過。",
    "SendDate": "2012\/06\/13",
    "SendNumber": "南議民政字第 1010010564號",
    "DoDesc": "依據臺南市政府中華民國101年6月27日府民生字第1010498028號函復：\r\n後甲公墓位處東區精忠段39-1地號等25筆土地，63、95地號所有權為私人、143地號為市政府所有，其餘39-1地號等22筆為國有財產局所有，該地段位處中華東路以東、中山高速公路以西、裕農路以北、小東路以南；慈幼高工、榮民醫院附近，土地面積8.23公頃，目前都市計畫為公墓用地，該公墓本府民政局已納入民國102年度遷葬期程研議，另配合東區整體設施、空間規劃，由都市發展局整體規劃辦理。",
    "AttList": [],
    "RAttList": [],
    "PdfDownloadUrl": "https:\/\/bill.tncc.gov.tw\/NoPaperMeeting_TNCC\/Api\/WEB015_GenerateProposal.ashx?prono=4efde47d-a594-4a22-a69d-a7ac8ee5450a&type=pdf",
    "CheckAttList": [],
    "DoneAttList": [],
    "ReDate": "",
    "ReDesc": "照審查意見通過。",
    "FirstDate": "",
    "FirstDesc": "",
    "SecondDate": "",
    "SecondDesc": "",
    "ThirdDate": "",
    "ThirdDesc": "",
    "ExecuteReDate": "",
    "ExecuteReNumber": "",
    "ExecuteReMemo": "依據臺南市政府中華民國101年6月27日府民生字第1010498028號函復：\r\n後甲公墓位處東區精忠段39-1地號等25筆土地，63、95地號所有權為私人、143地號為市政府所有，其餘39-1地號等22筆為國有財產局所有，該地段位處中華東路以東、中山高速公路以西、裕農路以北、小東路以南；慈幼高工、榮民醫院附近，土地面積8.23公頃，目前都市計畫為公墓用地，該公墓本府民政局已納入民國102年度遷葬期程研議，另配合東區整體設施、空間規劃，由都市發展局整體規劃辦理。",
    "ErrorMessage": ""
}