{
    "GradeTime": "第1屆 第5次 定期會",
    "PTypTitle": "保安",
    "CaseNumber": "4",
    "KidTitle": "市府提案-墊付款案",
    "ComeDate": "2013\/02\/27",
    "ComeNumber": "府觀府字第1020185965號",
    "OrgTitle": "臺南市政府觀光旅遊局",
    "OrgTitle2": "",
    "CaseCause": "交通部觀光局補助本府辦理「102年度觀光景點無縫隙旅遊服務-『台灣好行-88安平線及99台江線』」計畫經費新臺幣100萬元整，為爭取時效，謹請　貴會同意先行墊付，俾憑辦理後續相關採購作業事宜，俟102年度追加預算時再予轉正，敬請　審議。",
    "Content": "[{\"tag\":\"p\",\"content\":\"一、依據交通部觀光局102年2月8日觀旅字第10250003717號函辦理。\"},{\"tag\":\"p\",\"content\":\"二、本案符合各級地方政府墊付款處理要點第三條第四款：「經上級政府核定之補助款，所使用之支出。」規定。\"},{\"tag\":\"p\",\"content\":\"三、本案經交通部觀光局補助本府辦理「102年度觀光景點無縫隙旅遊服務-『台灣好行-88安平線及99台江線』」計畫，本府觀光旅遊局配合之行銷推廣及旅遊設施資訊相關建置費用計新臺幣100萬元整。因本案未及納入本府102年度預算，擬請准予辦理先行墊付，俟102年度追加預算時再予轉正。\"},{\"tag\":\"p\",\"content\":\"四、本案業經本府102年2月27日第102次市政會議通過，送請　貴會審議。\"}]",
    "Method": "[{\"tag\":\"p\",\"content\":\"敬請　貴會同意辦理先行墊付，俟102年度追加預算時再予轉正。\"}]",
    "CheckDate": "",
    "CheckDesc": "移請大會討論。",
    "DoneDate": "2013\/03\/12",
    "DoneDesc": "本會同意墊付。",
    "SendDate": "2013\/03\/15",
    "SendNumber": "南議保安字第 1020010146號",
    "DoDesc": "本案業於102年度臺南市地方總預算第一次追加減預算提出，並經貴會第一屆第八次臨時會審議通過。",
    "AttList": [],
    "RAttList": [],
    "PdfDownloadUrl": "https:\/\/bill.tncc.gov.tw\/NoPaperMeeting_TNCC\/Api\/WEB015_GenerateProposal.ashx?prono=cc5d7617-ef62-4a41-8d18-8aca0e4b8392&type=pdf",
    "CheckAttList": [],
    "DoneAttList": [],
    "ReDate": "",
    "ReDesc": "本會同意墊付。",
    "FirstDate": "2013\/03\/12",
    "FirstDesc": "",
    "SecondDate": "",
    "SecondDesc": "",
    "ThirdDate": "",
    "ThirdDesc": "",
    "ExecuteReDate": "",
    "ExecuteReNumber": "",
    "ExecuteReMemo": "本案業於102年度臺南市地方總預算第一次追加減預算提出，並經貴會第一屆第八次臨時會審議通過。",
    "ErrorMessage": ""
}