{
    "GradeTime": "第1屆 第5次 臨時會",
    "PTypTitle": "建設",
    "CaseNumber": "7",
    "KidTitle": "議員提案-一般提案",
    "ComeDate": "",
    "ComeNumber": "",
    "OrgTitle": "林志聰",
    "OrgTitle2": "",
    "CaseCause": "建請市府遷移新化果菜市場，以利地方發展。",
    "Content": "[{\"tag\":\"p\",\"content\":\"新化果菜市場為大台南主要水果批發市場，因市場空間狹小，使市場發展性不足，建請市府遷移市場以利新化果菜市場未來發展，並嘉惠果農。\"}]",
    "Method": "[{\"tag\":\"p\",\"content\":\"如案由。\"}]",
    "CheckDate": "",
    "CheckDesc": "照案通過。",
    "DoneDate": "2011\/08\/31",
    "DoneDesc": "照審查意見通過。",
    "SendDate": "2011\/09\/06",
    "SendNumber": "南議建設字第 1000011273號",
    "DoDesc": "本案經台南市政府100.09.15府農銷字第1000699969號函復：\r\n有關新化果菜市場之遷場規劃，本府業己請該公司協助覓尋交通便捷適合場地，期兼顧交通、農產品產銷便利及複合式多功能發展。\r\n-------------------------------------------------由於林議員全忠提出，新化果菜市場遷場攸關新化區之經濟發展，不應辦理遷移。將審慎考量農產品交易需求、地方民意、並就場地選址、經費來源等獲致共識後再作決定。\t",
    "AttList": [],
    "RAttList": [],
    "PdfDownloadUrl": "https:\/\/bill.tncc.gov.tw\/NoPaperMeeting_TNCC\/Api\/WEB015_GenerateProposal.ashx?prono=d69f2d82-361d-4919-b088-fc0d129b82d8&type=pdf",
    "CheckAttList": [],
    "DoneAttList": [],
    "ReDate": "",
    "ReDesc": "照審查意見通過。",
    "FirstDate": "",
    "FirstDesc": "",
    "SecondDate": "",
    "SecondDesc": "",
    "ThirdDate": "",
    "ThirdDesc": "",
    "ExecuteReDate": "",
    "ExecuteReNumber": "",
    "ExecuteReMemo": "本案經台南市政府100.09.15府農銷字第1000699969號函復：\r\n有關新化果菜市場之遷場規劃，本府業己請該公司協助覓尋交通便捷適合場地，期兼顧交通、農產品產銷便利及複合式多功能發展。\r\n-------------------------------------------------由於林議員全忠提出，新化果菜市場遷場攸關新化區之經濟發展，不應辦理遷移。將審慎考量農產品交易需求、地方民意、並就場地選址、經費來源等獲致共識後再作決定。\t",
    "ErrorMessage": ""
}