{
    "議案屆次別": "議案-第2屆第5次",
    "大會類別": "定期大會",
    "審查會別": "工務",
    "案號": "64",
    "提案類別": "議員提案",
    "來文日期": "",
    "來文字號": "",
    "提案單位\/人": [
        "陳怡珍"
    ],
    "連署人": [
        "賴惠員、蔡淑惠、郭信良"
    ],
    "主旨": "臺南市北區忠義路三段(自公園南路到成功路路段)水溝年久失修、老舊破損，影響地區排水效能，建請臺南市政府應儘速進行重新翻修工程，以維護市民居住權益。",
    "說明": "臺南市北區忠義路三段(自公園南路到成功路路段)水溝年久失修、老舊破損，無法維持排水功能，尤其遭逢汛期，一遇上豪大雨就導致大量積水，嚴重影響民眾居住環境。\n爰此，本席建請臺南市政府務必儘速完成水溝翻修工程，以維護市民居住權益。",
    "辦法": "如案由。",
    "審查意見": "請市府現勘後研議辦理。",
    "大會決議": "照審查意見通過。",
    "辦理情形": "本案經市府106年7月19日府工養一字第1060738714號函復：本府就「臺南市北區忠義路三段(自公園南路到成功路路段)水溝年久失修、老舊破損，影響地區排水效能，建請臺南市政府應儘速進行重新翻修工程」案，敬答覆如下：本府工務局於106 年4 月20 日會同三德里里長及北區區公所現場勘察，忠義路側溝（公園南路至成功路）現況功能尚屬完善，且未有淹水情況，惟部分溝蓋較為老舊但並不影響安全，本府先行錄案，並視明年經費編列狀況研議列入改善。",
    "決議日期": "2017\/6\/23",
    "發文日期": "2017\/7\/6",
    "發文字號": "南議工務字第1060004562號",
    "議會附件一": ""
}