{
    "GradeTime": "第2屆 第12次 臨時會",
    "PTypTitle": "法規",
    "CaseNumber": "7",
    "KidTitle": "查照\/備查案-法規查照案",
    "ComeDate": "2018\/10\/19",
    "ComeNumber": "府社人字第1071189412號",
    "OrgTitle": "臺南市政府社會局",
    "OrgTitle2": "",
    "CaseCause": "修正「臺南市政府社會局組織規程」第四條、第十三條、「臺南市政府社會局編制表」，請查照。",
    "Content": "[]",
    "Method": "[]",
    "CheckDate": "",
    "CheckDesc": "",
    "DoneDate": "",
    "DoneDesc": "",
    "SendDate": "2018\/12\/11",
    "SendNumber": "南議法規字第 1070008153號",
    "DoDesc": "",
    "AttList": [],
    "RAttList": [],
    "PdfDownloadUrl": "https:\/\/bill.tncc.gov.tw\/NoPaperMeeting_TNCC\/Api\/WEB015_GenerateProposal.ashx?prono=3b915d4d-3b0d-41cd-9d7e-0843af700adf&type=pdf",
    "CheckAttList": [],
    "DoneAttList": [],
    "ReDate": "",
    "ReDesc": "",
    "FirstDate": "2018\/11\/22",
    "FirstDesc": "",
    "SecondDate": "",
    "SecondDesc": "",
    "ThirdDate": "",
    "ThirdDesc": "",
    "ExecuteReDate": "",
    "ExecuteReNumber": "",
    "ExecuteReMemo": "",
    "ErrorMessage": ""
}