{
    "GradeTime": "第2屆 第8次 定期會",
    "PTypTitle": "法規",
    "CaseNumber": "3",
    "KidTitle": "查照\/備查案-法規查照案",
    "ComeDate": "2018\/05\/31",
    "ComeNumber": "府文永字第1070598770號",
    "OrgTitle": "臺南市政府文化局",
    "OrgTitle2": "",
    "CaseCause": "訂定「臺南市台江文化中心場地使用管理辦法」，請查照。",
    "Content": "[]",
    "Method": "[]",
    "CheckDate": "",
    "CheckDesc": "",
    "DoneDate": "2018\/07\/27",
    "DoneDesc": "同意備查。",
    "SendDate": "2018\/08\/13",
    "SendNumber": "南議法規字第 1070005544號",
    "DoDesc": "107年5月22日府法規字第1070569726A號令發布臺南市台江文化中心場地使用管理辦法。",
    "AttList": [],
    "RAttList": [],
    "PdfDownloadUrl": "https:\/\/bill.tncc.gov.tw\/NoPaperMeeting_TNCC\/Api\/WEB015_GenerateProposal.ashx?prono=d7de7dad-3d76-4fb3-a8e6-49e9fb16b36a&type=pdf",
    "CheckAttList": [],
    "DoneAttList": [],
    "ReDate": "",
    "ReDesc": "同意備查。",
    "FirstDate": "2018\/07\/12",
    "FirstDesc": "",
    "SecondDate": "",
    "SecondDesc": "",
    "ThirdDate": "",
    "ThirdDesc": "",
    "ExecuteReDate": "",
    "ExecuteReNumber": "",
    "ExecuteReMemo": "107年5月22日府法規字第1070569726A號令發布臺南市台江文化中心場地使用管理辦法。",
    "ErrorMessage": ""
}