{
    "GradeTime": "第4屆 第4次 定期會",
    "PTypTitle": "保安",
    "CaseNumber": "86",
    "KidTitle": "議員提案-一般提案",
    "ComeDate": "",
    "ComeNumber": "",
    "OrgTitle": "朱正軒",
    "OrgTitle2": "陳秋宏、余柷青、楊中成、李宗翰、林依婷、蔡蘇秋金、郭鴻儀",
    "CaseCause": "為改善市容環境與增加停車便利性，建請規劃永康區西橋里路外停車場北側髒亂點綠美化，並新增出入口以利動線改善。",
    "Content": "[{\"tag\":\"ol\",\"children\":[{\"order\":\"一、\",\"content\":\"西橋里柴頭港溪路外停車場北側，目前雜草叢生且堆置廢棄物，為整頓市容應規劃綠美化。\",\"children\":[]},{\"order\":\"二、\",\"content\":\"該場範圍廣大且狹長，並提供91格停車空間，然僅一處出入口，車輛進出不便，應於北側新增出入口。\",\"children\":[]}]}]",
    "Method": "[{\"tag\":\"p\",\"content\":\"如案由。\"}]",
    "CheckDate": "2024\/11\/22",
    "CheckDesc": "照案通過。",
    "DoneDate": "",
    "DoneDesc": "",
    "SendDate": "",
    "SendNumber": "",
    "DoDesc": "",
    "AttList": [],
    "RAttList": [],
    "PdfDownloadUrl": "https:\/\/bill.tncc.gov.tw\/NoPaperMeeting_TNCC\/Api\/WEB015_GenerateProposal.ashx?prono=6185522d-b1ce-428c-bdd6-9ccd100308cc&type=pdf",
    "CheckAttList": [],
    "DoneAttList": [],
    "ReDate": "",
    "ReDesc": "",
    "FirstDate": "",
    "FirstDesc": "",
    "SecondDate": "",
    "SecondDesc": "",
    "ThirdDate": "",
    "ThirdDesc": "",
    "ExecuteReDate": "",
    "ExecuteReNumber": "",
    "ExecuteReMemo": "",
    "ErrorMessage": ""
}