{
    "GradeTime": "第4屆 第1次 定期會",
    "PTypTitle": "工務",
    "CaseNumber": "49",
    "KidTitle": "議員提案-一般提案",
    "ComeDate": "",
    "ComeNumber": "",
    "OrgTitle": "盧崑福",
    "OrgTitle2": "Ingay Tali 穎艾達利、郭鴻儀、陳怡珍",
    "CaseCause": "建請重新鋪設建平十一街(府前四街至建平路路段)路面柏油。",
    "Content": "[{\"tag\":\"p\",\"content\":\"三、四十年久未修，路面嚴重破損，建請路面柏油重新鋪設，以維護用路人安全。\"}]",
    "Method": "[{\"tag\":\"p\",\"content\":\"建請工務局能儘速重新鋪設。\"}]",
    "CheckDate": "2023\/06\/02",
    "CheckDesc": "照案通過。",
    "DoneDate": "2023\/06\/07",
    "DoneDesc": "照審查意見通過。",
    "SendDate": "2023\/06\/15",
    "SendNumber": "南議工務字第 1120004410號",
    "DoDesc": "本府就「建請重新鋪設建平十一街(府前四街至建平路路段)路面柏油」案，敬答覆如下：\r\n本案業於112年5月19日完成會勘，建議改善路段面積約為1,068平方公尺，本府工務局先予錄案，並列入本府工務局各列管改善路段排程辦理。",
    "AttList": [],
    "RAttList": [],
    "PdfDownloadUrl": "https:\/\/bill.tncc.gov.tw\/NoPaperMeeting_TNCC\/Api\/WEB015_GenerateProposal.ashx?prono=fb9cfa96-8e71-4781-bf97-8582ed92f81f&type=pdf",
    "CheckAttList": [],
    "DoneAttList": [],
    "ReDate": "",
    "ReDesc": "照審查意見通過。",
    "FirstDate": "",
    "FirstDesc": "",
    "SecondDate": "",
    "SecondDesc": "",
    "ThirdDate": "",
    "ThirdDesc": "",
    "ExecuteReDate": "2023\/06\/30",
    "ExecuteReNumber": "府工務一字第 1120801238號",
    "ExecuteReMemo": "本府就「建請重新鋪設建平十一街(府前四街至建平路路段)路面柏油」案，敬答覆如下：\r\n本案業於112年5月19日完成會勘，建議改善路段面積約為1,068平方公尺，本府工務局先予錄案，並列入本府工務局各列管改善路段排程辦理。",
    "ErrorMessage": ""
}