{
    "GradeTime": "第4屆 第6次 定期會",
    "PTypTitle": "工務",
    "CaseNumber": "90",
    "KidTitle": "議員提案-一般提案",
    "ComeDate": "",
    "ComeNumber": "",
    "OrgTitle": "鄭佳欣、郭鴻儀",
    "OrgTitle2": "沈家鳳、蔡蘇秋金、陳怡珍、沈震東、蔡麗青、朱正軒、林依婷、林冠維、謝舒凡、黃麗招、余柷青、曾之婕",
    "CaseCause": "建請市府儘速辦理南352線(長榮街)道路拓寬及布袋里高齡橋改善工程。",
    "Content": "[{\"tag\":\"ol\",\"children\":[{\"order\":\"一、\",\"content\":\"南352線(長榮街，西起長大路口、東迄龜洞路段)為地方主要聯外道路，現況道路寬約8公尺，車流量大，且為連結台19甲及高雄路網的重要幹道，為改善通行效率與行車安全，建議將道路拓寬至15公尺。\",\"children\":[]},{\"order\":\"二、\",\"content\":\"布袋里高齡橋橋面過高，逢大雨易造成積水，影響通行便利與地方生活安全，需同步辦理改善。\",\"children\":[]},{\"order\":\"三、\",\"content\":\"本案原於111年底提報中央生活圈道路計畫，未獲核定，現配合南科管理局辦理「沙崙生態科學園區籌設計畫」，俟園區計畫通過後，預計將南352線長榮路拓寬案納入園區聯外道路公共建設計畫，爭取相關經費辦理(西起長大路口、東迄龜洞路段，經費約40億元)。經費概算：拓寬工程約1.5億元，用地費約0.46億元，總計約1.96億元；初步規劃長約980公尺，寬12〜15公尺，符合地方交通發展需求。\",\"children\":[]},{\"order\":\"四、\",\"content\":\"本席曾於2022年3月15日會勘協調南一高爾夫球場道路拓寬事宜，會議決議優先拓寬道路、改善橋梁及交通安全設施，後續持續追蹤進度。為保障民眾出行安全及提升地方交通效率，特請市府儘速辦理南352線道路拓寬及布袋里高齡橋改善工程，並配合「沙崙生態科學園區籌設計畫」，爭取中央及園區建設經費，加速工程施作時程。\",\"children\":[]}]}]",
    "Method": "[{\"tag\":\"p\",\"content\":\"如案由。\"}]",
    "CheckDate": "2025\/11\/28",
    "CheckDesc": "照案通過。",
    "DoneDate": "2025\/12\/04",
    "DoneDesc": "照審查意見通過。",
    "SendDate": "2025\/12\/12",
    "SendNumber": "南議工務字第 1140012256號",
    "DoDesc": "",
    "AttList": [],
    "RAttList": [],
    "PdfDownloadUrl": "https:\/\/bill.tncc.gov.tw\/NoPaperMeeting_TNCC\/Api\/WEB015_GenerateProposal.ashx?prono=2c9ea996-4004-484e-9eab-d505575159e2&type=pdf",
    "CheckAttList": [],
    "DoneAttList": [],
    "ReDate": "",
    "ReDesc": "照審查意見通過。",
    "FirstDate": "",
    "FirstDesc": "",
    "SecondDate": "",
    "SecondDesc": "",
    "ThirdDate": "",
    "ThirdDesc": "",
    "ExecuteReDate": "",
    "ExecuteReNumber": "",
    "ExecuteReMemo": "",
    "ErrorMessage": ""
}