{
    "GradeTime": "第4屆 第7次 定期會",
    "PTypTitle": "保安",
    "CaseNumber": "14",
    "KidTitle": "議員提案-一般提案",
    "ComeDate": "",
    "ComeNumber": "",
    "OrgTitle": "朱正軒",
    "OrgTitle2": "周嘉韋、沈家鳳、陳秋宏、陳皇宇、余柷青、李宗霖、李宗翰、謝舒凡、蔡筱薇、林依婷",
    "CaseCause": "建請針對機車車牌懸掛標準不一引發之執法爭議，統一取締標準，並研議建置「原廠及驗車資料庫比對系統」，以兼顧交通法治與合法車主權益。",
    "Content": "[{\"tag\":\"ol\",\"children\":[{\"order\":\"一、\",\"content\":\"近期發生多起停放路邊機車因「車牌懸掛角度」問題，遭警方逕行拖吊、拔牌並處以最高3.6萬元重罰。由於監理機關認定標準未隨修法同步更新，導致第一線執法缺乏明確標準，引發諸多民怨。\",\"children\":[]},{\"order\":\"二、\",\"content\":\"現行法規僅規定車牌「應正面懸掛於明顯適當位置」，以目視能「清楚辨識」為原則，並無具體懸掛角度規範。許多甫通過驗車或能被測速照相清楚拍攝車號的車輛仍遭開罰，讓基層員警執法陷入「自由心證」與不符比例原則的窘境。\",\"children\":[]},{\"order\":\"三、\",\"content\":\"警察局應與監理站於一週內召開協調會，針對目前的申訴案件、取締標準與實務作法進行跨單位研商，重新檢視對靜止車輛逕行拔牌的比例原則，並針對誤判案件儘速協助民眾進行行政救濟。\",\"children\":[]},{\"order\":\"四、\",\"content\":\"建請促請交通部、公路局與警政署等相關部會，共同研議建置「原廠及驗車資料庫比對系統」，將機車出廠原廠規格與監理站驗車通過時的數據及照片等數位資料，整合至警用載具系統中。\",\"children\":[]},{\"order\":\"五、\",\"content\":\"藉由科學化的系統連線比對，讓員警於執法前能即時確認牌架角度是否與原廠設定或最新驗車紀錄相符，精準取締惡意規避查緝的違規車輛，同時保障未改裝或已合法驗車車主之財產權益。\",\"children\":[]}]}]",
    "Method": "[{\"tag\":\"p\",\"content\":\"如案由。\"}]",
    "CheckDate": "2026\/06\/18",
    "CheckDesc": "函送市府研辦。",
    "DoneDate": "2026\/06\/24",
    "DoneDesc": "照審查意見通過。",
    "SendDate": "",
    "SendNumber": "",
    "DoDesc": "",
    "AttList": [],
    "RAttList": [],
    "PdfDownloadUrl": "https:\/\/bill.tncc.gov.tw\/NoPaperMeeting_TNCC\/Api\/WEB015_GenerateProposal.ashx?prono=27a8b687-f70c-4b3e-8a11-831f62e2b83d&type=pdf",
    "CheckAttList": [],
    "DoneAttList": [],
    "ReDate": "",
    "ReDesc": "照審查意見通過。",
    "FirstDate": "",
    "FirstDesc": "",
    "SecondDate": "",
    "SecondDesc": "",
    "ThirdDate": "",
    "ThirdDesc": "",
    "ExecuteReDate": "",
    "ExecuteReNumber": "",
    "ExecuteReMemo": "",
    "ErrorMessage": ""
}