{
    "GradeTime": "第3屆 第2次 定期會",
    "PTypTitle": "工務",
    "CaseNumber": "47",
    "KidTitle": "議員提案-一般提案",
    "ComeDate": "",
    "ComeNumber": "",
    "OrgTitle": "方一峰",
    "OrgTitle2": "周奕齊、周麗津、林美燕、曾培雅",
    "CaseCause": "市府針對大北門區（西港、佳里、七股、將軍、學甲、北門）社區公園進行總體檢，並逐年編列預算改善其環境與更新硬體設施，以提供社區里民安全又良好的休憩環境。",
    "Content": "[{\"tag\":\"p\",\"content\":\"一、許多社區公園及綠地因開發較早、使用頻繁，缺少整體規劃及維護，損壞也僅局部修繕，公園地墊老舊破損，健康器材亦缺乏管理及定期維護，減弱安全保護力，形成區民休閒安全隱憂，囿於經費難以符合各社區之期待。\"},{\"tag\":\"p\",\"content\":\"二、請市府針對上述問題提出整體規劃並編列經費逐年改善，使市民享有更安全的休憩環境。\"}]",
    "Method": "[{\"tag\":\"p\",\"content\":\"如案由。\"}]",
    "CheckDate": "2019\/11\/05",
    "CheckDesc": "請市府研議辦理。",
    "DoneDate": "2019\/12\/10",
    "DoneDesc": "照審查意見通過。",
    "SendDate": "2019\/12\/18",
    "SendNumber": "南議工務字第 1080010148號",
    "DoDesc": "本案經市府108年12月30日府工園二字第1081492214號函復：\r\n本府工務局將請各公所確認地方使用需求，後續再由各公所提送「臺南市政府工務局公共工程計畫提案單」向本府工務局申請經費辦理。",
    "AttList": [],
    "RAttList": [],
    "PdfDownloadUrl": "https:\/\/bill.tncc.gov.tw\/NoPaperMeeting_TNCC\/Api\/WEB015_GenerateProposal.ashx?prono=b6ee4323-688a-414e-b5aa-153e0e8e5801&type=pdf",
    "CheckAttList": [],
    "DoneAttList": [],
    "ReDate": "",
    "ReDesc": "照審查意見通過。",
    "FirstDate": "2019\/09\/23",
    "FirstDesc": "",
    "SecondDate": "",
    "SecondDesc": "",
    "ThirdDate": "",
    "ThirdDesc": "",
    "ExecuteReDate": "",
    "ExecuteReNumber": "",
    "ExecuteReMemo": "本案經市府108年12月30日府工園二字第1081492214號函復：\r\n本府工務局將請各公所確認地方使用需求，後續再由各公所提送「臺南市政府工務局公共工程計畫提案單」向本府工務局申請經費辦理。",
    "ErrorMessage": ""
}