{
    "GradeTime": "第3屆 第3次 定期會",
    "PTypTitle": "建設",
    "CaseNumber": "53",
    "KidTitle": "市府提案",
    "ComeDate": "2020\/06\/24",
    "ComeNumber": "府環廢字第1090756290號",
    "OrgTitle": "臺南市政府環境保護局",
    "OrgTitle2": "",
    "CaseCause": "行政院環境保護署核定本市辦理「臺南市垃圾篩分機械處理計畫」共計新臺幣4,150萬元整（中央補助款計3,486萬元整，市配合款計664萬元整），為爭取時效，惠請同意先行辦理墊付，俾憑辦理後續相關作業事宜，俟110年度總預算時辦理轉正，敬請審議。",
    "Content": "[{\"tag\":\"p\",\"content\":\"一、依據行政院環境保護署109年6月12日環署督字第1090044355號函辦理。\"},{\"tag\":\"p\",\"content\":\"二、本案符合「各機關單位預算執行要點」第44點第4款「經上級政府核定之補助款，所使用之支出」及第6款「配合上級或同級政府施政需要而核定必須分擔且須及時使用之支出」。\"},{\"tag\":\"p\",\"content\":\"三、本案相關說明：\"},{\"tag\":\"p\",\"content\":\"為賡續辦理本市廢棄物處理作業，環保署核定經費計新臺幣4,150萬元整（中央補助款計3,486萬元整，市配合款計664萬元整）。\"},{\"tag\":\"p\",\"content\":\"四、本案因中央核定計畫日期較晚，未及納入本府109年度總預算，為爭取時效，謹請貴會同意先行墊付。\"},{\"tag\":\"p\",\"content\":\"五、本案業經本府109年6月23日第444次市政會議審議通過。\"}]",
    "Method": "[{\"tag\":\"p\",\"content\":\"請貴會同意先行辦理墊付，俟110年度總預算時辦理轉正，敬請審議。\"}]",
    "CheckDate": "",
    "CheckDesc": "",
    "DoneDate": "2020\/07\/07",
    "DoneDesc": "同意墊付。",
    "SendDate": "2020\/07\/14",
    "SendNumber": "南議建設字第 1090005732號",
    "DoDesc": "",
    "AttList": [],
    "RAttList": [],
    "PdfDownloadUrl": "https:\/\/bill.tncc.gov.tw\/NoPaperMeeting_TNCC\/Api\/WEB015_GenerateProposal.ashx?prono=70253d0a-149e-4cec-ab97-5baa80b514b8&type=pdf",
    "CheckAttList": [],
    "DoneAttList": [],
    "ReDate": "",
    "ReDesc": "同意墊付。",
    "FirstDate": "2020\/04\/16",
    "FirstDesc": "",
    "SecondDate": "",
    "SecondDesc": "",
    "ThirdDate": "",
    "ThirdDesc": "",
    "ExecuteReDate": "",
    "ExecuteReNumber": "",
    "ExecuteReMemo": "",
    "ErrorMessage": ""
}