{
    "GradeTime": "第3屆 第2次 定期會",
    "PTypTitle": "保安",
    "CaseNumber": "19",
    "KidTitle": "議員提案-一般提案",
    "ComeDate": "",
    "ComeNumber": "",
    "OrgTitle": "沈震東、蔡筱薇",
    "OrgTitle2": "鄭佳欣",
    "CaseCause": "建請交通局將台南市北區小北段998-58及同段998-466興建複合型立體停車場。",
    "Content": "[{\"tag\":\"p\",\"content\":\"一、北區成德里當地有1988戶、人口有5635人，且當地連續5年人口增長，附近整體人口及戶數上升趨勢，而當地於成德停四免費公有停車場（即小北段998-58及同段998-466）僅有58格停車位，且長期為滿位狀況。\"},{\"tag\":\"p\",\"content\":\"二、且當地鄰近花園夜市等大型觀光景點，在特定時間停車位一位難尋。\"},{\"tag\":\"p\",\"content\":\"三、北區成德里因鄰里調整而導致活動中心不在里內，近兩萬人共用一個活動中心的狀況。\"},{\"tag\":\"p\",\"content\":\"四、爰此，建請交通局北區小北段998-58及同段998-466興建複合型立體停車場，以滿足居民停車與里民休憩活動的需求。\"}]",
    "Method": "[{\"tag\":\"p\",\"content\":\"如案由，請市府列為前瞻計劃預算辦理。\"}]",
    "CheckDate": "2019\/11\/04",
    "CheckDesc": "函送市府研辦。",
    "DoneDate": "2019\/12\/10",
    "DoneDesc": "照審查意見通過。",
    "SendDate": "2019\/12\/17",
    "SendNumber": "南議保安字第 1080011536號",
    "DoDesc": "本案經市府108年12月31日府交停管字第1081508539號函復:\r\n一、查案地已開闢成德停四免費停車場，為改善停車場長期車輛佔用問題，本府交通局業於108年12月3日派員與貴會沈議員震東、北區成德里辦公處完成會勘，決議將先進行該場鋪面改善工程後，再納入停車收費管理，以提升停車場周轉率及使用性。\r\n二、配合行政院前瞻基礎建設計畫期程，本府交通局業於108年11月15日提案申請立體多目標停車場新建工程經費補助，後續將依公路總局相關程序積極爭取計畫核定。\r\n-------------------------------------------------\r\n查公路總局第五區養護工程處（簡稱五工處）於108年12月4日辦理初審，刻依初審會議意見辦理交通調查以充實計畫書內容，3月底回覆五工處，後續依審查結果辦理。",
    "AttList": [],
    "RAttList": [],
    "PdfDownloadUrl": "https:\/\/bill.tncc.gov.tw\/NoPaperMeeting_TNCC\/Api\/WEB015_GenerateProposal.ashx?prono=1179bc72-6677-4196-a320-fabab6e708c1&type=pdf",
    "CheckAttList": [],
    "DoneAttList": [],
    "ReDate": "",
    "ReDesc": "照審查意見通過。",
    "FirstDate": "2019\/09\/23",
    "FirstDesc": "",
    "SecondDate": "",
    "SecondDesc": "",
    "ThirdDate": "",
    "ThirdDesc": "",
    "ExecuteReDate": "",
    "ExecuteReNumber": "",
    "ExecuteReMemo": "本案經市府108年12月31日府交停管字第1081508539號函復:\r\n一、查案地已開闢成德停四免費停車場，為改善停車場長期車輛佔用問題，本府交通局業於108年12月3日派員與貴會沈議員震東、北區成德里辦公處完成會勘，決議將先進行該場鋪面改善工程後，再納入停車收費管理，以提升停車場周轉率及使用性。\r\n二、配合行政院前瞻基礎建設計畫期程，本府交通局業於108年11月15日提案申請立體多目標停車場新建工程經費補助，後續將依公路總局相關程序積極爭取計畫核定。\r\n-------------------------------------------------\r\n查公路總局第五區養護工程處（簡稱五工處）於108年12月4日辦理初審，刻依初審會議意見辦理交通調查以充實計畫書內容，3月底回覆五工處，後續依審查結果辦理。",
    "ErrorMessage": ""
}