{
    "GradeTime": "第3屆 第4次 定期會",
    "PTypTitle": "工務",
    "CaseNumber": "41",
    "KidTitle": "議員提案-一般提案",
    "ComeDate": "",
    "ComeNumber": "",
    "OrgTitle": "蔡蘇秋金",
    "OrgTitle2": "郭鴻儀、蔡筱薇、李鎮國、李偉智、李宗翰、沈震東、楊中成、陳昆和、邱莉莉、劉米山",
    "CaseCause": "建請將佳里區公園路(文化路至復興路段)兩側道路，列為路平專案儘速改善，以維護民眾通行安全。",
    "Content": "[{\"tag\":\"p\",\"content\":\"佳里區公園路(文化路至復興路段)兩側道路，為佳里區重要道路，但多處破損、久未改善，建請工務局將此路段列為路平專案儘速改善，以維護民眾通行安全。\"}]",
    "Method": "[{\"tag\":\"p\",\"content\":\"如案由。\"}]",
    "CheckDate": "2020\/11\/26",
    "CheckDesc": "請市府研議辦理。",
    "DoneDate": "2020\/12\/01",
    "DoneDesc": "照審查意見通過。",
    "SendDate": "2020\/12\/08",
    "SendNumber": "南議工務字第 1090011697號",
    "DoDesc": "本案經市府110年1月5日府工養二字第1091601138號函復：\r\n本案本府工務局已於109年12月22日邀集蔡蘇秋金議員服務處、區公所現場勘查，路面因長年使用老舊，尤其文化路至新生路段老舊龜裂明顯，後續請佳里區公所依現況需求提案並先行搶修坑洞處，本府工務局錄案後將視年度預算研議辦理。",
    "AttList": [],
    "RAttList": [],
    "PdfDownloadUrl": "https:\/\/bill.tncc.gov.tw\/NoPaperMeeting_TNCC\/Api\/WEB015_GenerateProposal.ashx?prono=e496684a-d177-4d6c-948b-d6ac8dc6d56a&type=pdf",
    "CheckAttList": [],
    "DoneAttList": [],
    "ReDate": "",
    "ReDesc": "照審查意見通過。",
    "FirstDate": "2020\/09\/15",
    "FirstDesc": "",
    "SecondDate": "",
    "SecondDesc": "",
    "ThirdDate": "",
    "ThirdDesc": "",
    "ExecuteReDate": "",
    "ExecuteReNumber": "",
    "ExecuteReMemo": "本案經市府110年1月5日府工養二字第1091601138號函復：\r\n本案本府工務局已於109年12月22日邀集蔡蘇秋金議員服務處、區公所現場勘查，路面因長年使用老舊，尤其文化路至新生路段老舊龜裂明顯，後續請佳里區公所依現況需求提案並先行搶修坑洞處，本府工務局錄案後將視年度預算研議辦理。",
    "ErrorMessage": ""
}