{
    "GradeTime": "第3屆 第3次 定期會",
    "PTypTitle": "民政",
    "CaseNumber": "15",
    "KidTitle": "議員提案-一般提案",
    "ComeDate": "",
    "ComeNumber": "",
    "OrgTitle": "李鎮國",
    "OrgTitle2": "尤榮智、蔡淑惠、王家貞、Ingay Tali穎艾達利",
    "CaseCause": "建請市府編列預算興建光復里里活動中心，以利居民休閒暨舉辦各項活動之需。",
    "Content": "[{\"tag\":\"p\",\"content\":\"一、永康區光復里因眷村改建遷移，目前戶數278戶、人口578人，現眷改基地皆已標售，地方快速發展建設中，缺乏活動中心，所有活動辦理(含投票)須向其他里借用場地。\"},{\"tag\":\"p\",\"content\":\"二、今有消防局復興分隊旁光復里鄰里公園（永興段379-380、405-409），地點適中、適於活動休閒之用，詳如附件。\"}]",
    "Method": "[{\"tag\":\"p\",\"content\":\"如案由。\"}]",
    "CheckDate": "2020\/06\/01",
    "CheckDesc": "照案通過。",
    "DoneDate": "2020\/06\/09",
    "DoneDesc": "照審查意見通過。",
    "SendDate": "2020\/06\/16",
    "SendNumber": "南議民政字第 1090004172號",
    "DoDesc": "收文字號：109年7月6日1090005276號\r\n依據臺南市政府109年7月3日府民自字第1090727169號函復：\r\n本府就「建請市府編列預算興建光復里里活動中心，以利居民休閒暨舉辦各項活動之需。」案，敬答覆如下：\r\n一、有關永康區光復里活動中心興建預定地為永興段379、380、381、405、406、407、408、409及410地號等9筆土地，目前已取得國有財產署及本府工務局同意利用都市計畫公共設施用地多目標使用辦法興建活動中心。\r\n二、永康區公所提報109年新興計畫總工程費2,520萬，其中規劃設計監造費182萬元，109年先行編列100萬1,000元辦理規劃設計，餘監造費81萬9,000元及工程款將於110年起分年編列。\r\n三、本案委由區公所辦理，並於109年6月30日第一次開標(招標資料修正後)，廠商投標文件符合規定，採購評選委員會議擇期召開。\r\n",
    "AttList": [
        {
            "DownloadURL": "https:\/\/bill.tncc.gov.tw\/NoPaperMeeting_TNCC\/Api\/WEB017_DownloadFile.ashx?attno=6807e30a-f406-40c6-a4c7-d979ee2746bd",
            "FileName": "光復里活動中心預定用地.pdf",
            "ErrorMessage": ""
        }
    ],
    "RAttList": [],
    "PdfDownloadUrl": "https:\/\/bill.tncc.gov.tw\/NoPaperMeeting_TNCC\/Api\/WEB015_GenerateProposal.ashx?prono=0ef5b078-037f-466b-b5c5-d6ff96178c15&type=pdf",
    "CheckAttList": [],
    "DoneAttList": [],
    "ReDate": "",
    "ReDesc": "照審查意見通過。",
    "FirstDate": "2020\/04\/16",
    "FirstDesc": "",
    "SecondDate": "",
    "SecondDesc": "",
    "ThirdDate": "",
    "ThirdDesc": "",
    "ExecuteReDate": "",
    "ExecuteReNumber": "",
    "ExecuteReMemo": "收文字號：109年7月6日1090005276號\r\n依據臺南市政府109年7月3日府民自字第1090727169號函復：\r\n本府就「建請市府編列預算興建光復里里活動中心，以利居民休閒暨舉辦各項活動之需。」案，敬答覆如下：\r\n一、有關永康區光復里活動中心興建預定地為永興段379、380、381、405、406、407、408、409及410地號等9筆土地，目前已取得國有財產署及本府工務局同意利用都市計畫公共設施用地多目標使用辦法興建活動中心。\r\n二、永康區公所提報109年新興計畫總工程費2,520萬，其中規劃設計監造費182萬元，109年先行編列100萬1,000元辦理規劃設計，餘監造費81萬9,000元及工程款將於110年起分年編列。\r\n三、本案委由區公所辦理，並於109年6月30日第一次開標(招標資料修正後)，廠商投標文件符合規定，採購評選委員會議擇期召開。\r\n",
    "ErrorMessage": ""
}