{
    "GradeTime": "第3屆 第4次 臨時會",
    "PTypTitle": "民政",
    "CaseNumber": "20",
    "KidTitle": "市府提案",
    "ComeDate": "2020\/01\/07",
    "ComeNumber": "府研智字第1090066964號",
    "OrgTitle": "臺南市政府研究發展考核委員會",
    "OrgTitle2": "",
    "CaseCause": "國家發展委員會「109年補助地方政府資訊應用實施計畫」核定本市辦理「運用MyData建置一站式整合服務平台計畫」經費新台幣530萬元整乙案(中央補助330萬元；市配合款200萬元)，為爭取時效，謹請貴會同意先行墊付330萬元，俾憑辦理後續相關作業事宜，俟110年度總預算時辦理轉正，敬請審議。",
    "Content": "[{\"tag\":\"p\",\"content\":\"一、依據國發會108年12月6日發資字第1081501940號函補助審核「通過」暨國發會108年12月27日發資字第1080027498號函核定「同意辦理」等通知辦理。\"},{\"tag\":\"p\",\"content\":\"二、本案符合「各機關單位預算執行要點」第44點第4、6款，經上級政府核定之補助款所使用之支出與配合上級或同級政府施政需要而核定必須分擔且須及時使用之支出。\"},{\"tag\":\"p\",\"content\":\"三、本案相關說明：\"},{\"tag\":\"p\",\"content\":\"本案總經費新台幣530萬元整(中央補助款330萬元、市配合款200萬元)，其中330萬元的中央補助款，因未及納入本府109年度總預算，為爭取時效，謹請貴會同意先行墊付。另本市配合款200萬元，已編列於109年度本府智慧發展中心預算。\"},{\"tag\":\"p\",\"content\":\"四、本案業經本府109年1月7日第421次市政會議審議通過。\"}]",
    "Method": "[{\"tag\":\"p\",\"content\":\"請貴會同意先行辦理墊付，俟110年度總預算時辦理轉正。\"}]",
    "CheckDate": "2020\/01\/14",
    "CheckDesc": "聯席審查意見：同意墊付。",
    "DoneDate": "2020\/01\/17",
    "DoneDesc": "照聯席審查意見通過。",
    "SendDate": "2020\/01\/22",
    "SendNumber": "南議民政字第 1090000873號",
    "DoDesc": "",
    "AttList": [],
    "RAttList": [],
    "PdfDownloadUrl": "https:\/\/bill.tncc.gov.tw\/NoPaperMeeting_TNCC\/Api\/WEB015_GenerateProposal.ashx?prono=d1db4ddb-4b3d-4605-82fe-358d5c22a6db&type=pdf",
    "CheckAttList": [],
    "DoneAttList": [],
    "ReDate": "",
    "ReDesc": "照聯席審查意見通過。",
    "FirstDate": "2020\/01\/08",
    "FirstDesc": "",
    "SecondDate": "",
    "SecondDesc": "",
    "ThirdDate": "",
    "ThirdDesc": "",
    "ExecuteReDate": "",
    "ExecuteReNumber": "",
    "ExecuteReMemo": "",
    "ErrorMessage": ""
}